ct_serialcommands/__init__.py
ct_serialcommands/find_port.py
ct_serialcommands/serialcommands.py
ct_serialcommands/serialcommands_blocking.py
ct_serialcommands-0.1.0.dist-info/LICENSE
ct_serialcommands-0.1.0.dist-info/METADATA
ct_serialcommands-0.1.0.dist-info/WHEEL
ct_serialcommands-0.1.0.dist-info/top_level.txt
ct_serialcommands-0.1.0.dist-info/RECORD
