Metadata-Version: 2.1
Name: ct-serialcommands
Version: 0.1.0
Summary: A Python module for seamless serial communication with devices like an Arduino or ESP, offering both non-blocking and blocking interfaces with customizable command and value callbacks.
Home-page: https://github.com/clevrthings/SerialCommands
Author: Clevrthings
Author-email: info@clevrthings.com
Classifier: Programming Language :: Python :: 3
Classifier: License :: OSI Approved :: MIT License
Classifier: Operating System :: OS Independent
Requires-Python: >=3.6
License-File: LICENSE
